setup.py
distributions_jtgz95/Binomialdistribution.py
distributions_jtgz95/Gaussiandistribution.py
distributions_jtgz95/Generaldistribution.py
distributions_jtgz95/__init__.py
distributions_jtgz95.egg-info/PKG-INFO
distributions_jtgz95.egg-info/SOURCES.txt
distributions_jtgz95.egg-info/dependency_links.txt
distributions_jtgz95.egg-info/not-zip-safe
distributions_jtgz95.egg-info/top_level.txt