Metadata-Version: 1.0
Name: distributions-jtgz95
Version: 0.1
Summary: Gaussian and bionomial distributions
Home-page: UNKNOWN
Author: UNKNOWN
Author-email: myemail@email.com
License: UNKNOWN
Platform: UNKNOWN
